qg_aio_eureka/__init__.py
qg_aio_eureka/client.py
qg_aio_eureka/exc.py
qg_aio_eureka/log.py
qg_aio_eureka-0.1.2.dist-info/METADATA
qg_aio_eureka-0.1.2.dist-info/WHEEL
qg_aio_eureka-0.1.2.dist-info/top_level.txt
qg_aio_eureka-0.1.2.dist-info/RECORD
